flask_discussion/__init__.py
flask_discussion/templates/flask_discussion/disqus.html
flask_discussion/templates/flask_discussion/helper.html
flask_discussion/templates/flask_discussion/isso.html
flask_discussion/templates/flask_discussion/remark42.html
Flask_Discussion-0.1.1.dist-info/LICENSE
Flask_Discussion-0.1.1.dist-info/METADATA
Flask_Discussion-0.1.1.dist-info/WHEEL
Flask_Discussion-0.1.1.dist-info/top_level.txt
Flask_Discussion-0.1.1.dist-info/RECORD
