Metadata-Version: 2.1
Name: Flask-Discussion
Version: 0.1.1
Summary: Comment system integration for Flask applications
Home-page: https://github.com/rmed/flask-discussion
Author: Rafael Medina García
Author-email: rafamedgar@gmail.com
License: MIT
Keywords: flask discussion comments commenting
Platform: UNKNOWN
Classifier: Development Status :: 4 - Beta
Classifier: Framework :: Flask
Classifier: Intended Audience :: Developers
Classifier: License :: OSI Approved :: MIT License
Classifier: Programming Language :: Python
